py_algorithms/__init__.py
py_algorithms/_version.py
py_algorithms/dynamic_connectivity.py
py_algorithms/utils.py
py_algorithms/array/__init__.py
py_algorithms/array/circular_array.py
py_algorithms/challenges/__init__.py
py_algorithms/challenges/challenges.py
py_algorithms/challenges/coderbyte/__init__.py
py_algorithms/challenges/coderbyte/array_addition.py
py_algorithms/challenges/coderbyte/binary_search_tree_lca.py
py_algorithms/challenges/coderbyte/power_set.py
py_algorithms/challenges/coderbyte/sp_in_unweigted_graph.py
py_algorithms/challenges/coderbyte/subset_sum.py
py_algorithms/challenges/coderbyte/two_sum.py
py_algorithms/challenges/coderbyte/weighted_path.py
py_algorithms/challenges/hackerrank/__init__.py
py_algorithms/challenges/hackerrank/the_love_letter_mistery.py
py_algorithms/challenges/various/__init__.py
py_algorithms/challenges/various/quarantine/__init__.py
py_algorithms/challenges/various/quarantine/arrays/__init__.py
py_algorithms/challenges/various/quarantine/arrays/_sum_swap.py
py_algorithms/challenges/various/quarantine/dp/__init__.py
py_algorithms/challenges/various/quarantine/dp/_count_transformations.py
py_algorithms/challenges/various/quarantine/dp/_possible_change_ways.py
py_algorithms/data_structures/__init__.py
py_algorithms/data_structures/deque.py
py_algorithms/data_structures/doubly_linked_list_deque.py
py_algorithms/data_structures/heap.py
py_algorithms/data_structures/max_heap.py
py_algorithms/data_structures/min_heap.py
py_algorithms/data_structures/priority_queue.py
py_algorithms/data_structures/queue.py
py_algorithms/data_structures/stack.py
py_algorithms/data_structures/suffix_array.py
py_algorithms/data_structures/tree_node.py
py_algorithms/graph/__init__.py
py_algorithms/graph/connected_components.py
py_algorithms/graph/dijkstra_shortest_path.py
py_algorithms/graph/reconstruct_dijkstra_path_tree.py
py_algorithms/graph/topological_sort.py
py_algorithms/graph/adt/__init__.py
py_algorithms/graph/adt/edge.py
py_algorithms-0.26.1.dist-info/LICENSE
py_algorithms-0.26.1.dist-info/METADATA
py_algorithms-0.26.1.dist-info/WHEEL
py_algorithms-0.26.1.dist-info/top_level.txt
py_algorithms-0.26.1.dist-info/RECORD
