Metadata-Version: 2.1
Name: py-algorithms
Version: 0.26.1
Summary: Library of Algorithms, Data Structures, variety of solutions to common CS problems.
Home-page: https://github.com/rlishtaba/py-algorithms
Author: Roman Lishtaba
Author-email: roman@lishtaba.com
License: MIT
Keywords: algorithm,algorithms,data structure,data structures,data structures python,containers,heaps,heap sort,sorting algorithms,graphs,graph algorithms,hashing,python,selection sort,selectionsort,merge sort,mergesort,bubble sort,bubblesort,quick sort,quick-sort,quicksort,qsort,binary search,heap,fibonacci heap,max heap,min heap,priority queue,fibonacci priority queue,max priority queue,min priority queue,dynamic connectivity,union find,quick union,weighted quick union,weighted quick union wit
Platform: UNKNOWN
Classifier: Programming Language :: Python
Classifier: Programming Language :: Python :: 3
Classifier: License :: OSI Approved :: MIT License
Classifier: Operating System :: OS Independent
Classifier: Environment :: Other Environment
Classifier: Intended Audience :: Developers
Classifier: Topic :: Software Development :: Libraries :: Python Modules
Classifier: Development Status :: 4 - Beta
Requires-Dist: packaging (>=16)
Requires-Dist: PyYAML (<4,>=3)
Requires-Dist: six (<2,>=1)
